# (三)
## part1
-XX:+TraceClassLoading追踪类的加载信息
`注意追踪的是类的加载的信息,而不是类的初始化的信息`
```
[Loaded java.lang.Object from /usr/java/jdk1.8.0_161/jre/lib/rt.jar]
...........省略
[Loaded com.ccy.test04.Test01 from file:/home/chengcongyue/idea-workspace/java8/out/production/java8/]
...........省略
[Loaded com.ccy.test04.Parent from file:/home/chengcongyue/idea-workspace/java8/out/production/java8/]
[Loaded com.ccy.test04.Child from file:/home/chengcongyue/idea-workspace/java8/out/production/java8/]
This is Parent static blocking!!!
parent str
[Loaded java.lang.Shutdown from /usr/java/jdk1.8.0_161/jre/lib/rt.jar]
[Loaded java.lang.Shutdown$Lock from /usr/java/jdk1.8.0_161/jre/lib/rt.jar]
```
我们发现尽管没有调用child的static块,两个类还是都初始化了
-三种设置方式:
```
-XX:+<option> 开始option选项
-XX:-<option> 结束option选项
-XX:<option>=<value>
```
## part2
```
public class Test01 {

    public static void main(String[] args) {
        System.out.println(Child.str);
    }
}

class Parent
{
    public static final String str="parent str";//在上面的代码加上final

    static{
        System.out.println("This is Parent static blocking!!!");
    }
}
class Child extends Parent
{
    static{
        System.out.println("This is Child static blocking!!!");
    }
}
```
`常量在编译阶段会存入到调用这个常量方法所在类的常量池中`,这一道题就将这个常量在Test01的常量池中
**我们可以将编译之后的Child和Parent的class文件删除,也可以运行成功**
## part3
记录几个助记符
public static final int i=1;
```
   0: getstatic     #2                  // Field java/lang/System.out:Ljava/io/PrintStream;
   3: iconst_1                          // 将数字1从常量池放入栈顶
   4: invokevirtual #4                  // Method java/io/PrintStream.println:(I)V
```
`iconst_1-----iconst_5分别表示将数字1---5从常量池放入栈顶`
```
       0: getstatic     #2                  // Field java/lang/System.out:Ljava/io/PrintStream;
       3: ldc           #4                  // String parent str
       5: invokevirtual #5                  // Method java/io/PrintStream.println:(Ljava/lang/String;)V

```
`表示将int,float或者String类型的常量池从常量池中推送到栈顶`
```
       0: getstatic     #2                  // Field java/lang/System.out:Ljava/io/PrintStream;
       3: bipush        127
       5: invokevirtual #4                  // Method java/io/PrintStream.println:(I)V
```
表示将-127-----128从常量池放入到栈顶
```
       0: getstatic     #2                  // Field java/lang/System.out:Ljava/io/PrintStream;
       3: sipush        128
       6: invokevirtual #4                  // Method java/io/PrintStream.println:(I)V
```
将-32768---32767从常量池放入到栈顶
```
iconst_1----iconst_5
sipush
bipush
```